{
  "frame_key": "global_2025_10_09_20_17_01_540.json",
  "question": "Within a 100-meter radius, What are the overall exterior dimensions of the vehicle that is closest to me right now?",
  "ego_id": "AVflow.2",
  "target_ids": [
    "flow1.27",
    "flow4.12",
    "flow4.13",
    "flow6.5",
    "flow5.14",
    "flow5.13",
    "flow7.5",
    "flow4.14",
    "flow5.12",
    "flow2.29"
  ],
  "size": [
    12.0,
    5.0,
    5.0,
    5.0,
    5.0,
    12.0,
    5.0,
    5.0,
    5.0,
    12.0
  ],
  "subtask": "Size",
  "check": "around_check",
  "label_id": 8
}